canvasrobot/__init__.py
canvasrobot/canvasrobot.py
canvasrobot/canvasrobot_model.py
canvasrobot/commandline.py
canvasrobot/commandline_model.py
canvasrobot/index.html
canvasrobot/minimal.py
canvasrobot/need_more_values_warning.py
canvasrobot/urltransform.py
canvasrobot/assets/redirect_list.xlsx
canvasrobot/entities/__init__.py
canvasrobot/entities/course.py
canvasrobot/entities/guest.py
canvasrobot/entities/py.typed
canvasrobot/entities/quiz.py
canvasrobot/entities/user.py
canvasrobot-0.9.0.dist-info/METADATA
canvasrobot-0.9.0.dist-info/WHEEL
canvasrobot-0.9.0.dist-info/entry_points.txt
canvasrobot-0.9.0.dist-info/RECORD
