Metadata-Version: 2.4
Name: canvasrobot
Version: 0.9.0
Summary: Library which uses Canvasapi (see https://canvasapi.readthedocs.io) to provide a CanvasRobot class.
Author-email: Nico de Groot <ndegroot0@gmail.com>
Requires-Python: <4.0.0,>=3.9
Requires-Dist: arrow<2.0.0,>=1.3.0
Requires-Dist: attrs>=24.2.0
Requires-Dist: bs4>=0.0.2
Requires-Dist: canvasapi>=3.3.0
Requires-Dist: ftfy>=6.3.1
Requires-Dist: keyring>=25.5.0
Requires-Dist: lxml>=5.3.0
Requires-Dist: openpyxl>=3.1.5
Requires-Dist: pydal>=20241204.1
Requires-Dist: pytz<2025.0,>=2024.2
Requires-Dist: pywebview<6.0.0,>=5.3.2
Requires-Dist: pyyaml>=6.0.2
Requires-Dist: requests>=2.25.1
Requires-Dist: result>=0.17.0
Requires-Dist: rich-click>=1.8.4
Requires-Dist: rich>=13.9.4
